jupyter_widget_echo_testing/__init__.py
jupyter_widget_echo_testing/_frontend.py
jupyter_widget_echo_testing/_version.py
jupyter_widget_echo_testing/example.py
jupyter_widget_echo_testing/labextension/build_log.json
jupyter_widget_echo_testing/labextension/package.json
jupyter_widget_echo_testing/labextension/static/lib_index_js.658c6e484e5652eab79b.js
jupyter_widget_echo_testing/labextension/static/lib_index_js.658c6e484e5652eab79b.js.map
jupyter_widget_echo_testing/labextension/static/lib_plugin_js.6df5262c9aac6e976c16.js
jupyter_widget_echo_testing/labextension/static/lib_plugin_js.6df5262c9aac6e976c16.js.map
jupyter_widget_echo_testing/labextension/static/lib_widget_js.460cec08a8be554339ac.js
jupyter_widget_echo_testing/labextension/static/lib_widget_js.460cec08a8be554339ac.js.map
jupyter_widget_echo_testing/labextension/static/lib_widget_js.9429b5aa3845bdf64123.js
jupyter_widget_echo_testing/labextension/static/lib_widget_js.9429b5aa3845bdf64123.js.map
jupyter_widget_echo_testing/labextension/static/remoteEntry.0c386c59e3bc71f4db98.js
jupyter_widget_echo_testing/labextension/static/remoteEntry.0c386c59e3bc71f4db98.js.map
jupyter_widget_echo_testing/labextension/static/remoteEntry.77c3ae861fced833caff.js
jupyter_widget_echo_testing/labextension/static/remoteEntry.77c3ae861fced833caff.js.map
jupyter_widget_echo_testing/labextension/static/style.js
jupyter_widget_echo_testing/nbextension/extension.js
jupyter_widget_echo_testing/nbextension/index.js
jupyter_widget_echo_testing/nbextension/index.js.map
jupyter_widget_echo_testing/tests/__init__.py
jupyter_widget_echo_testing/tests/conftest.py
jupyter_widget_echo_testing/tests/test_example.py
jupyter_widget_echo_testing/tests/test_nbextension_path.py
jupyter_widget_echo_testing-0.1.2.data/data/etc/jupyter/nbconfig/notebook.d/jupyter_widget_echo_testing.json
jupyter_widget_echo_testing-0.1.2.data/data/share/jupyter/labextensions/jupyter-widget-echo-testing/build_log.json
jupyter_widget_echo_testing-0.1.2.dist-info/LICENSE.txt
jupyter_widget_echo_testing-0.1.2.dist-info/METADATA
jupyter_widget_echo_testing-0.1.2.dist-info/WHEEL
jupyter_widget_echo_testing-0.1.2.dist-info/top_level.txt
jupyter_widget_echo_testing-0.1.2.dist-info/RECORD
